heavyball/__init__.py
heavyball/chainable.py
heavyball/helpers.py
heavyball/utils.py
heavyball-2.2.3.dist-info/licenses/LICENSE
heavyball-2.2.3.dist-info/METADATA
heavyball-2.2.3.dist-info/WHEEL
heavyball-2.2.3.dist-info/top_level.txt
heavyball-2.2.3.dist-info/RECORD
