Metadata-Version: 2.4
Name: heavyball
Version: 2.2.3
Summary: Efficient Optimizers
Author-email: HeavyBall Authors <github.heavyball@nestler.sh>
Project-URL: source, https://github.com/HomebrewML/HeavyBall
Project-URL: tracker, https://github.com/HomebrewML/HeavyBall/issues
Keywords: torch,optimizer,muon,soap,psgd
Classifier: Intended Audience :: Developers
Classifier: Intended Audience :: Science/Research
Classifier: License :: OSI Approved :: BSD License
Classifier: Natural Language :: English
Classifier: Operating System :: OS Independent
Classifier: Programming Language :: Python :: 3
Requires-Python: >=3.9
License-File: LICENSE
Requires-Dist: opt-einsum>=3.4.0
Requires-Dist: torch<3.0,>=2.2
Requires-Dist: numpy>=2.3.4
Provides-Extra: dev
Requires-Dist: pre-commit; extra == "dev"
Requires-Dist: pytest; extra == "dev"
Requires-Dist: hypothesis; extra == "dev"
Requires-Dist: ruff; extra == "dev"
Requires-Dist: matplotlib; extra == "dev"
Requires-Dist: seaborn; extra == "dev"
Requires-Dist: pandas; extra == "dev"
Requires-Dist: typer; extra == "dev"
Requires-Dist: optuna; extra == "dev"
Requires-Dist: optunahub; extra == "dev"
Requires-Dist: hebo; extra == "dev"
Requires-Dist: lightbench; extra == "dev"
Dynamic: license-file
